piles/__init__.py
piles/base.py
piles/check.py
piles/convert.py
piles/graph.py
piles/hybrid.py
piles/tracking.py
piles/tree.py
piles/utilities.py
piles-0.1.0.dist-info/LICENSE
piles-0.1.0.dist-info/WHEEL
piles-0.1.0.dist-info/METADATA
piles-0.1.0.dist-info/RECORD
