Metadata-Version: 2.1
Name: piles
Version: 0.1.0
Summary: lightweight, flexible, extensible python composite data structures
Home-page: https://github.com/WithPrecedent/piles
License: Apache
Author: Corey Rayburn Yung
Author-email: coreyrayburnyung@gmail.com
Requires-Python: >=3.9,<4.0
Classifier: License :: Other/Proprietary License
Classifier: Programming Language :: Python :: 3
Classifier: Programming Language :: Python :: 3.9
Requires-Dist: bunches (>=0.1.0,<0.2.0)
Requires-Dist: more-itertools (>=8.10.0,<9.0.0)
Project-URL: Repository, https://github.com/WithPrecedent/piles
